LICENSE
README.md
lyyguifunction.py
setup.py
lyyguifunction.egg-info/PKG-INFO
lyyguifunction.egg-info/SOURCES.txt
lyyguifunction.egg-info/dependency_links.txt
lyyguifunction.egg-info/requires.txt
lyyguifunction.egg-info/top_level.txt